psr_demo/__init__.py
psr_demo-0.10.1.dist-info/WHEEL
psr_demo-0.10.1.dist-info/entry_points.txt
psr_demo-0.10.1.dist-info/METADATA
psr_demo-0.10.1.dist-info/RECORD
