Metadata-Version: 2.4
Name: psr-demo
Version: 0.10.1
Summary: Demo project for python-semantic-release
Keywords: semantic version,semantic release,ci/cd,convetional commits,python-semantic-release
Author: fleetingbytes
Author-email: fleetingbytes <7075397+fleetingbytes@users.noreply.github.com>
License-Expression: BSD-2-Clause
Classifier: Development Status :: 7 - Inactive
Classifier: License :: OSI Approved :: BSD License
Classifier: Programming Language :: Python :: 3.11
Classifier: Programming Language :: Unix Shell
Classifier: Topic :: Software Development :: Version Control :: Git
Requires-Python: >=3.11
Project-URL: Changelog, http://github.com/fleetingbytes/psr-demo/blob/master/CHANGELOG.md
Project-URL: Documentation, http://github.com/fleetingbytes/psr-demo/blob/master/README.md
Project-URL: Homepage, http://github.com/fleetingbytes/psr-demo
Project-URL: Issues, http://github.com/fleetingbytes/psr-demo/issues
Project-URL: Repository, http://github.com/fleetingbytes/psr-demo.git
